code_understanding/__init__.py
code_understanding/config.py
code_understanding/logging_config.py
code_understanding/analysis/complexity.py
code_understanding/config/config.yaml
code_understanding/context/__init__.py
code_understanding/context/builder.py
code_understanding/context/extended_repo_map.py
code_understanding/context/extractor.py
code_understanding/mcp/__init__.py
code_understanding/mcp/server/__init__.py
code_understanding/mcp/server/app.py
code_understanding/pattern_search/searcher.py
code_understanding/repository/__init__.py
code_understanding/repository/cache.py
code_understanding/repository/documentation.py
code_understanding/repository/manager.py
code_understanding/repository/path_utils.py
code_understanding/repository/file_filtering/__init__.py
code_understanding/repository/file_filtering/repo_filter.py
code_understanding/resources/language_extensions.txt
mcp_code_understanding-0.1.2.dist-info/METADATA
mcp_code_understanding-0.1.2.dist-info/WHEEL
mcp_code_understanding-0.1.2.dist-info/entry_points.txt
mcp_code_understanding-0.1.2.dist-info/top_level.txt
mcp_code_understanding-0.1.2.dist-info/RECORD
