Metadata-Version: 2.4
Name: mcp-code-understanding
Version: 0.1.2
Summary: MCP server for code understanding and context generation
Author-email: Tim Kitchens <codingthefuturewithai@gmail.com>
License: MIT
Classifier: Development Status :: 3 - Alpha
Classifier: Intended Audience :: Developers
Classifier: License :: OSI Approved :: MIT License
Classifier: Programming Language :: Python :: 3
Classifier: Programming Language :: Python :: 3.11
Classifier: Programming Language :: Python :: 3.12
Classifier: Topic :: Software Development :: Libraries :: Python Modules
Requires-Python: <3.13,>=3.11
Requires-Dist: mcp>=1.0.0
Requires-Dist: mcp[cli]>=1.0.0
Requires-Dist: gitpython>=3.1.0
Requires-Dist: langchain>=0.3.0
Requires-Dist: aiohttp>=3.8.0
Requires-Dist: pyyaml>=6.0
Requires-Dist: typing-extensions>=4.5.0
Requires-Dist: pytest>=7.4.0
Requires-Dist: pytest-asyncio>=0.21.0
Requires-Dist: pytest-cov>=4.1.0
Requires-Dist: pathspec>=0.12.1
Requires-Dist: aider-chat==0.82.1
Requires-Dist: identify>=2.5.35
Requires-Dist: lizard>=1.17.24
Requires-Dist: debugpy>=1.8.1
Requires-Dist: platformdirs>=4.2.0
Provides-Extra: dev
Requires-Dist: pytest>=7.4.0; extra == "dev"
Requires-Dist: pytest-asyncio>=0.21.0; extra == "dev"
Requires-Dist: pytest-cov>=4.1.0; extra == "dev"
Requires-Dist: black>=23.12.0; extra == "dev"
Requires-Dist: isort>=5.13.0; extra == "dev"
Requires-Dist: mypy>=1.8.0; extra == "dev"
Requires-Dist: pre-commit>=3.5.0; extra == "dev"
